escape_rucio_policy_package/__init__.py
escape_rucio_policy_package/permission.py
escape_rucio_policy_package/schema.py
escape_rucio_policy_package-0.2.2.dist-info/licenses/LICENSE
escape_rucio_policy_package-0.2.2.dist-info/METADATA
escape_rucio_policy_package-0.2.2.dist-info/WHEEL
escape_rucio_policy_package-0.2.2.dist-info/top_level.txt
escape_rucio_policy_package-0.2.2.dist-info/RECORD
