Metadata-Version: 2.4
Name: escape_rucio_policy_package
Version: 0.2.2
Summary: Rucio policy package for the ESCAPE collaboration
Author-email: ESCAPE CERN <escape-cern-ops@cern.ch>
Classifier: Programming Language :: Python :: 3
Classifier: Operating System :: OS Independent
Requires-Python: >=3.9
License-File: LICENSE
Dynamic: license-file
